jlcpcbexporter/__init__.py
jlcpcbexporter/main.py
jlcpcbexporter/py.typed
jlcpcbexporter-1.0.0.dist-info/0BSD.txt
jlcpcbexporter-1.0.0.dist-info/LICENSE
jlcpcbexporter-1.0.0.dist-info/METADATA
jlcpcbexporter-1.0.0.dist-info/MIT.txt
jlcpcbexporter-1.0.0.dist-info/WHEEL
jlcpcbexporter-1.0.0.dist-info/entry_points.txt
jlcpcbexporter-1.0.0.dist-info/top_level.txt
jlcpcbexporter-1.0.0.dist-info/RECORD
