Metadata-Version: 2.1
Name: jlcpcbexporter
Version: 1.0.0
Summary: Exporter of JLCPCB compatible files from EAGLE CAM files
Home-page: https://github.com/Flameeyes/jlcpcbexporter
Author: Diego Elio Pettenò
Author-email: flameeyes@flameeyes.com
License: MIT
Keywords: pcb,jlcpcb,eagle
Platform: UNKNOWN
Classifier: Development Status :: 4 - Beta
Classifier: License :: OSI Approved :: MIT License
Classifier: Operating System :: OS Independent
Classifier: Programming Language :: Python
Classifier: Programming Language :: Python :: 3
Requires-Python: ~=3.7
Requires-Dist: click
Provides-Extra: dev
Requires-Dist: mypy ; extra == 'dev'
Requires-Dist: pre-commit ; extra == 'dev'
Requires-Dist: setuptools-scm ; extra == 'dev'
